README.md
setup.py
quarc/__init__.py
quarc/_version.py
quarc/quarc.py
quarc/security.py
quarc/unused.py
quarc.egg-info/PKG-INFO
quarc.egg-info/SOURCES.txt
quarc.egg-info/dependency_links.txt
quarc.egg-info/entry_points.txt
quarc.egg-info/requires.txt
quarc.egg-info/top_level.txt