Metadata-Version: 1.0
Name: quarc
Version: 0.1.8
Summary: Open a Quarc Gateway
Home-page: https://quarc.services/
Author: Simon Biggs
Author-email: mail@simonbiggs.net
License: AGPL3+
Platform: UNKNOWN
